cloudflarepycli/__init__.py
cloudflarepycli/__main__.py
cloudflarepycli/cloudflareclass.py
cloudflare_speedtest-1.8.2.dist-info/METADATA
cloudflare_speedtest-1.8.2.dist-info/WHEEL
cloudflare_speedtest-1.8.2.dist-info/entry_points.txt
cloudflare_speedtest-1.8.2.dist-info/top_level.txt
cloudflare_speedtest-1.8.2.dist-info/RECORD
