Metadata-Version: 2.1
Name: cloudflare-speedtest
Version: 1.8.2
Summary: "Python CLI and python class for retrieving user's realtime performance statistics"
Home-page: https://github.com/tevslin/cloudflarepycli
Author: "Tom Evslin"
Author-email: tevslin@gmail.com
Project-URL: Bug Tracker, https://github.com/tevslin/cloudflarepycli/issues
Keywords: speedtest,cloudflare,latency,jitter
Classifier: Programming Language :: Python :: 3
Classifier: License :: OSI Approved :: GNU General Public License v3 (GPLv3)
Classifier: Operating System :: OS Independent
Requires-Python: >=3.7
Requires-Dist: requests
